usr.v
module universal_shift_register (
    input clk,
    input reset,              // CLR input in schema
    input [1:0] select,       // S1 and S0 
    input [3:0] parallel_in,  // I3 ınputs
    input serial_in_left,     // Rıghtmost Mux I2 ınput
    input serial_in_right,    // Leftmost Mux I1 ınput
    output reg [3:0] q        // Output
);

    always @(posedge clk or posedge reset) begin
        if (reset) begin
            q <= 4'b0000;
        end else begin
            case (select)
                2'b00: q <= q;                         // Hold (I0)
                2'b01: q <= {serial_in_right, q[3:1]}; // Shift Right (I1)
                2'b10: q <= {q[2:0], serial_in_left};  // Shift Left (I2)
                2'b11: q <= parallel_in;               // Parallel Load (I3)
            endcase
        end
    end
endmodule

usr_tb.v
`timescale 1ns/1ps

module usr_tb;
    // Define inputs as 'reg' and outputs as 'wire'
    reg clk, reset, s_in_l, s_in_r;
    reg [1:0] sel;
    reg [3:0] p_in;
    wire [3:0] q_out;

    // Instantiate the designed module
    universal_shift_register uut (
        .clk(clk), .reset(reset), .select(sel),
        .parallel_in(p_in), .serial_in_left(s_in_l),
        .serial_in_right(s_in_r), .q(q_out)
    );

    // Clock Generation: toggles every 5ns (100MHz)
    initial begin
        clk = 0;
        forever #5 clk = ~clk;
    end

    // Test Scenario
    initial begin
        // GTKWave için dalga formu dosyasını oluştur [cite: 185]
        $dumpfile("usr_result.vcd");
        $dumpvars(0, usr_tb);

        reset = 1; #15; reset = 0;     // 1. Reset State
        
        sel = 2'b11; p_in = 4'b1010; #10; // 2. Parallel Load: Load '1010'
        
        sel = 2'b00; #20;  // 3. Hold: Keep the value for 20ns
        
        // 4. Shift Right: Shift with '1' entering from the right
        sel = 2'b01; s_in_r = 1; #10; // Expected: 1101
        #10;                        // Expected: 1110
        
        sel = 2'b10; s_in_l = 1; #10; // 5. Shift Left: Shift with '0' entering from the left
        #10;

        $display("Simulasyon tamamlandi. GTKWave ile vcd dosyasini inceleyin.");
        $finish; // End the simulation
    end
endmodule

usr_result.vcd
$date
	Mon May 04 14:58:50 2026
$end
$version
	Icarus Verilog
$end
$timescale
	1ps
$end
$scope module usr_tb $end
$var wire 4 ! q_out [3:0] $end
$var reg 1 " clk $end
$var reg 4 # p_in [3:0] $end
$var reg 1 $ reset $end
$var reg 1 % s_in_l $end
$var reg 1 & s_in_r $end
$var reg 2 ' sel [1:0] $end
$scope module uut $end
$var wire 1 " clk $end
$var wire 4 ( parallel_in [3:0] $end
$var wire 1 $ reset $end
$var wire 2 ) select [1:0] $end
$var wire 1 % serial_in_left $end
$var wire 1 & serial_in_right $end
$var reg 4 * q [3:0] $end
$upscope $end
$upscope $end
$enddefinitions $end
$comment Show the parameter values. $end
$dumpall
$end
#0
$dumpvars
b0 *
bx )
bx (
bx '
x&
x%
1$
bx #
0"
b0 !
$end
#5000
1"
#10000
0"
#15000
b1010 !
b1010 *
1"
b1010 #
b1010 (
b11 '
b11 )
0$
#20000
0"
#25000
1"
b0 '
b0 )
#30000
0"
#35000
1"
#40000
0"
#45000
b1101 !
b1101 *
1"
1&
b1 '
b1 )
#50000
0"
#55000
b1110 !
b1110 *
1"
#60000
0"
#65000
b1101 !
b1101 *
1"
1%
b10 '
b10 )
#70000
0"
#75000
b1011 !
b1011 *
1"
#80000
0"
#85000
b111 !
b111 *
1"
